installer/__init__.py
installer/__main__.py
installer/_bootstrap.py
installer/run.py
lib/__init__.py
lib/_meter.py
lib/_trace.py
lib/mxl_tracker.py
mxl_project-0.1.0.dist-info/METADATA
mxl_project-0.1.0.dist-info/WHEEL
mxl_project-0.1.0.dist-info/RECORD
